presidio/__init__.py
presidio/analyzer.py
presidio/anonymizer.py
presidio/evaluator.py
presidio/image.py
presidio/structured.py
presidio-0.2.1.dist-info/licenses/LICENSE
presidio-0.2.1.dist-info/METADATA
presidio-0.2.1.dist-info/WHEEL
presidio-0.2.1.dist-info/top_level.txt
presidio-0.2.1.dist-info/RECORD
