Metadata-Version: 2.4
Name: presidio
Version: 0.2.1
Summary: Unified wrapper and convenience facade for the Microsoft Presidio ecosystem.
Author-email: Developers at PaperCloud Tech <developers@papercloud.tech>
License: MIT
Project-URL: Homepage, https://github.com/papercloudtech/presidio
Keywords: presidio,pii,data-privacy,anonymization,redaction,nlp,security
Classifier: License :: OSI Approved :: MIT License
Classifier: Programming Language :: Python :: 3
Classifier: Programming Language :: Python :: 3 :: Only
Classifier: Programming Language :: Python :: 3.9
Classifier: Programming Language :: Python :: 3.10
Classifier: Programming Language :: Python :: 3.11
Classifier: Programming Language :: Python :: 3.12
Classifier: Intended Audience :: Developers
Classifier: Topic :: Security
Classifier: Topic :: Software Development :: Libraries
Classifier: Topic :: Text Processing
Requires-Python: >=3.9
License-File: LICENSE
Requires-Dist: presidio-analyzer
Requires-Dist: presidio-anonymizer
Requires-Dist: presidio-evaluator
Requires-Dist: presidio-image-redactor
Requires-Dist: presidio-structured
Provides-Extra: analyzer
Requires-Dist: presidio-analyzer; extra == "analyzer"
Provides-Extra: anonymization
Requires-Dist: presidio-analyzer; extra == "anonymization"
Requires-Dist: presidio-anonymizer; extra == "anonymization"
Provides-Extra: evaluation
Requires-Dist: presidio-evaluator; extra == "evaluation"
Provides-Extra: image
Requires-Dist: presidio-image-redactor; extra == "image"
Provides-Extra: structured
Requires-Dist: presidio-structured; extra == "structured"
Provides-Extra: all
Dynamic: license-file
